quap/__init__.py
quap/quap.py
test/__init__.py
test/test_quap.py
pymc3_quap-1.0.2.dist-info/LICENSE
pymc3_quap-1.0.2.dist-info/METADATA
pymc3_quap-1.0.2.dist-info/WHEEL
pymc3_quap-1.0.2.dist-info/top_level.txt
pymc3_quap-1.0.2.dist-info/RECORD
