Metadata-Version: 2.1
Name: pymc3-quap
Version: 1.0.2
Summary: Quadratic approximation for PyMC3
Home-page: https://github.com/rasmusbergpalm/pymc3-quap
Author: Rasmus Berg Palm
Author-email: rasmusbergpalm@gmail.com
License: UNKNOWN
Platform: UNKNOWN
Classifier: Programming Language :: Python :: 3
Classifier: License :: OSI Approved :: MIT License
Classifier: Operating System :: OS Independent
